command_system/Command.py
command_system/CommandChain.py
command_system/CommandLifecycle.py
command_system/CommandQueue.py
command_system/CommandResponse.py
command_system/Dependencies.py
command_system/__init__.py
command_system/py.typed
command_system-0.2.3.dist-info/WHEEL
command_system-0.2.3.dist-info/METADATA
command_system-0.2.3.dist-info/RECORD
