Metadata-Version: 2.4
Name: command-system
Version: 0.2.3
Summary: Type-safe command pattern implementation in pure Python
Keywords: command
Author: Alec Zaiane
License-Expression: MIT
Requires-Python: >=3.11
Project-URL: Repository, https://github.com/alec-zaiane/command-system/
